PIRS/__init__.py
PIRS/rank.py
PIRS/simulations.py
PIRS-0.1.1.dist-info/METADATA
PIRS-0.1.1.dist-info/WHEEL
PIRS-0.1.1.dist-info/top_level.txt
PIRS-0.1.1.dist-info/RECORD
