Metadata-Version: 2.1
Name: PIRS
Version: 0.1.1
Summary: Prediction Interval Ranking Score
Home-page: https://github.com/aleccrowell/PIRS
Author: Alec Crowell
Author-email: alexander.m.crowell@gmail.com
License: BSD-3
Download-URL: https://github.com/aleccrowell/PIRS/releases/tag/v0.1.1
Keywords: circadian,time series,constitutive expression,bioinformatics
Platform: UNKNOWN
Requires-Dist: numpy
Requires-Dist: pandas
Requires-Dist: scipy
Requires-Dist: sklearn
Requires-Dist: tqdm
Requires-Dist: seaborn
